synthexa_rpa/__init__.py
synthexa_rpa/application/config.py
synthexa_rpa/application/logger.py
synthexa_rpa/application/orchestrator.py
synthexa_rpa/application/run.py
synthexa_rpa/application/gateway/orchestrator_gateway.py
synthexa_rpa/infra/gateway/orchestrator_gateway/supabase.py
synthexa_rpa-0.0.4.dist-info/LICENSE
synthexa_rpa-0.0.4.dist-info/METADATA
synthexa_rpa-0.0.4.dist-info/WHEEL
synthexa_rpa-0.0.4.dist-info/top_level.txt
synthexa_rpa-0.0.4.dist-info/RECORD
