Metadata-Version: 2.2
Name: synthexa-rpa
Version: 0.0.4
Summary: A simple RPA library for Python
Author-email: Vitor Gabriel <vitorg.34825@gmail.com>, Matheus Cascão <matheusfranco23@hotmail.com>
Classifier: Programming Language :: Python :: 3
Classifier: License :: OSI Approved :: MIT License
Classifier: Operating System :: OS Independent
Requires-Python: >=3.10
License-File: LICENSE
Requires-Dist: pydantic==2.8.2
Requires-Dist: supabase==2.7.4
